{"nodes": [{"id": "community_module", "label": "community.module.ts", "file_type": "code", "source_file": "/Users/mac/pim/cognicare/backend-v2/src/modules/community/community.module.ts", "source_location": "L1"}, {"id": "community_module_communitymodule", "label": "CommunityModule", "file_type": "code", "source_file": "/Users/mac/pim/cognicare/backend-v2/src/modules/community/community.module.ts", "source_location": "L49"}], "edges": [{"source": "community_module", "target": "common", "relation": "imports_from", "confidence": "EXTRACTED", "source_file": "/Users/mac/pim/cognicare/backend-v2/src/modules/community/community.module.ts", "source_location": "L1", "weight": 1.0}, {"source": "community_module", "target": "mongoose", "relation": "imports_from", "confidence": "EXTRACTED", "source_file": "/Users/mac/pim/cognicare/backend-v2/src/modules/community/community.module.ts", "source_location": "L2", "weight": 1.0}, {"source": "community_module", "target": "post_schema", "relation": "imports_from", "confidence": "EXTRACTED", "source_file": "/Users/mac/pim/cognicare/backend-v2/src/modules/community/community.module.ts", "source_location": "L3", "weight": 1.0}, {"source": "community_module", "target": "comment_schema", "relation": "imports_from", "confidence": "EXTRACTED", "source_file": "/Users/mac/pim/cognicare/backend-v2/src/modules/community/community.module.ts", "source_location": "L7", "weight": 1.0}, {"source": "community_module", "target": "post_repository_interface", "relation": "imports_from", "confidence": "EXTRACTED", "source_file": "/Users/mac/pim/cognicare/backend-v2/src/modules/community/community.module.ts", "source_location": "L11", "weight": 1.0}, {"source": "community_module", "target": "comment_repository_interface", "relation": "imports_from", "confidence": "EXTRACTED", "source_file": "/Users/mac/pim/cognicare/backend-v2/src/modules/community/community.module.ts", "source_location": "L12", "weight": 1.0}, {"source": "community_module", "target": "post_mongo_repository", "relation": "imports_from", "confidence": "EXTRACTED", "source_file": "/Users/mac/pim/cognicare/backend-v2/src/modules/community/community.module.ts", "source_location": "L13", "weight": 1.0}, {"source": "community_module", "target": "comment_mongo_repository", "relation": "imports_from", "confidence": "EXTRACTED", "source_file": "/Users/mac/pim/cognicare/backend-v2/src/modules/community/community.module.ts", "source_location": "L14", "weight": 1.0}, {"source": "community_module", "target": "create_post_use_case", "relation": "imports_from", "confidence": "EXTRACTED", "source_file": "/Users/mac/pim/cognicare/backend-v2/src/modules/community/community.module.ts", "source_location": "L15", "weight": 1.0}, {"source": "community_module", "target": "get_posts_use_case", "relation": "imports_from", "confidence": "EXTRACTED", "source_file": "/Users/mac/pim/cognicare/backend-v2/src/modules/community/community.module.ts", "source_location": "L16", "weight": 1.0}, {"source": "community_module", "target": "update_post_use_case", "relation": "imports_from", "confidence": "EXTRACTED", "source_file": "/Users/mac/pim/cognicare/backend-v2/src/modules/community/community.module.ts", "source_location": "L17", "weight": 1.0}, {"source": "community_module", "target": "delete_post_use_case", "relation": "imports_from", "confidence": "EXTRACTED", "source_file": "/Users/mac/pim/cognicare/backend-v2/src/modules/community/community.module.ts", "source_location": "L18", "weight": 1.0}, {"source": "community_module", "target": "toggle_like_use_case", "relation": "imports_from", "confidence": "EXTRACTED", "source_file": "/Users/mac/pim/cognicare/backend-v2/src/modules/community/community.module.ts", "source_location": "L19", "weight": 1.0}, {"source": "community_module", "target": "get_comments_use_case", "relation": "imports_from", "confidence": "EXTRACTED", "source_file": "/Users/mac/pim/cognicare/backend-v2/src/modules/community/community.module.ts", "source_location": "L20", "weight": 1.0}, {"source": "community_module", "target": "add_comment_use_case", "relation": "imports_from", "confidence": "EXTRACTED", "source_file": "/Users/mac/pim/cognicare/backend-v2/src/modules/community/community.module.ts", "source_location": "L21", "weight": 1.0}, {"source": "community_module", "target": "get_like_status_use_case", "relation": "imports_from", "confidence": "EXTRACTED", "source_file": "/Users/mac/pim/cognicare/backend-v2/src/modules/community/community.module.ts", "source_location": "L22", "weight": 1.0}, {"source": "community_module", "target": "upload_post_image_use_case", "relation": "imports_from", "confidence": "EXTRACTED", "source_file": "/Users/mac/pim/cognicare/backend-v2/src/modules/community/community.module.ts", "source_location": "L23", "weight": 1.0}, {"source": "community_module", "target": "community_controller", "relation": "imports_from", "confidence": "EXTRACTED", "source_file": "/Users/mac/pim/cognicare/backend-v2/src/modules/community/community.module.ts", "source_location": "L24", "weight": 1.0}, {"source": "community_module", "target": "community_module_communitymodule", "relation": "contains", "confidence": "EXTRACTED", "source_file": "/Users/mac/pim/cognicare/backend-v2/src/modules/community/community.module.ts", "source_location": "L49", "weight": 1.0}]}