{"nodes": [{"id": "sw", "label": "sw.js", "file_type": "code", "source_file": "/Users/mac/pim/cognicareweb/src/sw.js", "source_location": "L1"}], "edges": [{"source": "sw", "target": "workbox_core", "relation": "imports_from", "confidence": "EXTRACTED", "source_file": "/Users/mac/pim/cognicareweb/src/sw.js", "source_location": "L1", "weight": 1.0}, {"source": "sw", "target": "workbox_cacheable_response", "relation": "imports_from", "confidence": "EXTRACTED", "source_file": "/Users/mac/pim/cognicareweb/src/sw.js", "source_location": "L2", "weight": 1.0}, {"source": "sw", "target": "workbox_expiration", "relation": "imports_from", "confidence": "EXTRACTED", "source_file": "/Users/mac/pim/cognicareweb/src/sw.js", "source_location": "L3", "weight": 1.0}, {"source": "sw", "target": "workbox_precaching", "relation": "imports_from", "confidence": "EXTRACTED", "source_file": "/Users/mac/pim/cognicareweb/src/sw.js", "source_location": "L4", "weight": 1.0}, {"source": "sw", "target": "workbox_routing", "relation": "imports_from", "confidence": "EXTRACTED", "source_file": "/Users/mac/pim/cognicareweb/src/sw.js", "source_location": "L5", "weight": 1.0}, {"source": "sw", "target": "workbox_strategies", "relation": "imports_from", "confidence": "EXTRACTED", "source_file": "/Users/mac/pim/cognicareweb/src/sw.js", "source_location": "L6", "weight": 1.0}]}